LICENSE
MANIFEST.in
README.md
command_line_ping3.py
enums.py
errors.py
ping3.py
setup.cfg
setup.py
ping3df.egg-info/PKG-INFO
ping3df.egg-info/SOURCES.txt
ping3df.egg-info/dependency_links.txt
ping3df.egg-info/entry_points.txt
ping3df.egg-info/top_level.txt