Metadata-Version: 1.2
Name: ping3df
Version: 2.4.0.post1
Summary: A pure python3 version of ICMP ping implementation using raw socket.
Home-page: https://github.com/onlineque/ping3
Author: Kai Yan ; forked and modified by Vladimir Siman
Author-email: kai@kyan001.com
License: MIT
Keywords: python3 ping icmp socket tool
Platform: UNKNOWN
Classifier: Development Status :: 5 - Production/Stable
Classifier: Intended Audience :: Developers
Classifier: Intended Audience :: End Users/Desktop
Classifier: Topic :: System :: Networking
Classifier: License :: OSI Approved :: MIT License
Classifier: Programming Language :: Python :: 3
Classifier: Programming Language :: Python :: 3.3
Classifier: Programming Language :: Python :: 3.4
Classifier: Programming Language :: Python :: 3.5
Classifier: Programming Language :: Python :: 3.6
Classifier: Programming Language :: Python :: 3.7
Classifier: Programming Language :: Python :: 3 :: Only
Requires-Python: >=3
